{
  "USAF": 1,
  "AIR FORCE": 1,
  "UAF": 2,
  "FAIRBANKS": 2,
  "UAA": 3,
  "ANCHORAGE": 3,
  "AIC": 4,
  "AMERICAN INTERNATIONAL": 4,
  "ASU": 5,
  "ARIZONA STATE": 5,
  "ARMY": 6,
  "AGUS": 7,
  "AUGUSTANA": 7,
  "BSU": 8,
  "BEMIDJI STATE": 8,
  "BENT": 9,
  "BENTLEY": 9,
  "BC": 10,
  "BOSTON COLLEGE": 10,
  "BU": 11,
  "BOSTON": 11,
  "BOSTON UNIVERSITY": 11,
  "BGSU": 12,
  "BOWLING GREEN": 12,
  "BRWN": 13,
  "BROWN": 13,
  "CANI": 14,
  "CANISIUS": 14,
  "CLRK": 15,
  "CLARKSON": 15,
  "COLG": 16,
  "COLGATE": 16,
  "CC": 17,
  "COLORADO COLLEGE": 17,
  "COLORADO": 17,
  "CONN": 18,
  "UCONN": 18,
  "COR": 19,
  "CORNELL": 19,
  "DART": 20,
  "DARTMOUTH": 20,
  "DU": 21,
  "DENVER": 21,
  "DENVER UNIVERSITY": 21,
  "FRST": 22,
  "FERRIS STATE": 22,
  "HARV": 23,
  "HARVARD": 23,
  "HC": 24,
  "HOLY CROSS": 24,
  "LSS": 25,
  "LAKE SUPERIOR": 25,
  "LAKE SUPERIOR STATE": 25,
  "LIND": 26,
  "LINDENWOOD": 26,
  "LIU": 27,
  "LONG ISLAND": 27,
  "LONG ISLAND UNIVERSITY": 27,
  "ME": 28,
  "MAINE": 28,
  "MASS": 29,
  "UMASS": 29,
  "UML": 30,
  "UMASS-LOWELL": 30,
  "UMASS LOWELL": 30,
  "MRCY": 31,
  "MERCYHURST": 31,
  "MRMK": 32,
  "MERRIMACK": 32,
  "MIAO": 33,
  "MIAMI OHIO": 33,
  "MICH": 34,
  "MICHIGAN": 34,
  "MSU": 35,
  "MICHIGAN STATE": 35,
  "MTU": 36,
  "MICHIGAN TECH": 36,
  "MINN": 37,
  "MINNESOTA": 37,
  "MND": 38,
  "MINNESOTA DULUTH": 38,
  "MNSU": 39,
  "MINNESOTA STATE": 39,
  "UNH": 40,
  "NEW ": 40,
  "NEW HAMPSHIRE": 40,
  "NU": 41,
  "NIAGARA": 41,
  "NIAGARA UNIVERSITY": 41,
  "UND": 42,
  "NORTH DAKOTA": 42,
  "NE": 43,
  "NORTHEASTEN": 43,
  "NMU": 44,
  "NORTHERN MICHIGAN": 44,
  "ND": 45,
  "NOTRE DAME": 45,
  "OSU": 46,
  "OHIO STATE": 46,
  "UNO": 47,
  "NEBRASKA-OMAHA": 47,
  "NEBRASKA OMAHA": 47,
  "OMAHA": 47,
  "PNST": 48,
  "PENN STATE": 48,
  "PRIN": 49,
  "PRINCETON": 49,
  "PROV": 50,
  "PROVIDENCE": 50,
  "QUIN": 51,
  "QUINNIPIAC": 51,
  "RPI": 52,
  "RMU": 53,
  "ROBERT MORRIS": 53,
  "RIT": 54,
  "ROCHESTER": 54,
  "SHU": 55,
  "SACRED HEART": 55,
  "STCL": 56,
  "ST. CLOUD STATE": 56,
  "ST CLOUD STATE": 56,
  "SAINT CLOUD STATE": 56,
  "CLOUD STATE": 56,
  "STL": 57,
  "ST. LAWRENCE": 57,
  "ST LAWRENCE": 57,
  "SAINT LAWRENCE": 57,
  "LAWRENCE": 57,
  "STMN": 58,
  "ST. THOMAS": 58,
  "ST THOMAS": 58,
  "SAINT THOMAS": 58,
  "THOMAS": 58,
  "STON": 59,
  "STONEHILL": 59,
  "UNION": 60,
  "VT": 61,
  "VERMONT": 61,
  "WMU": 62,
  "WESTERN MICHIGAN": 62,
  "WISC": 63,
  "WISCONSIN": 63,
  "YALE": 64,
  "TNST": 65,
  "TENNESSEE STATE": 65,
  "BING": 66,
  "BINGHAMTON": 66,
  "SFU": 67,
  "SIMON FRASER": 67,
  "UAH": 68,
  "ALABAMA-HUNTSVILLE": 68,
  "ALABAMA HUNTSVILLE": 68,
  "UNLV": 69,
  "OLAF": 70,
  "ST. OLAF": 70,
  "ST OLAF": 70,
  "SAINT OLAF": 70,
  "WVU": 71,
  "WEST VIRGINIA": 71,
  "MINOT": 72,
  "MINOT STATE": 72
}
